uistylelang/__init__.py
uistylelang/context.py
uistylelang/lang.py
uistylelang/utils.py
uistylelang/widgets.py
uistylelang-0.8.5.dist-info/LICENSE
uistylelang-0.8.5.dist-info/METADATA
uistylelang-0.8.5.dist-info/WHEEL
uistylelang-0.8.5.dist-info/top_level.txt
uistylelang-0.8.5.dist-info/RECORD
