Metadata-Version: 2.1
Name: uistylelang
Version: 0.8.5
Summary: Simple CSS-like language which allows for drawing and styling wxPython elements.
Home-page: https://github.com/Correct-Syntax/ui-style-lang
Author: Noah Rahm, Correct Syntax
Author-email: correctsyntax@yahoo.com
License: BSD 3-Clause
Keywords: wxPython,css,language,user interface,GUI,drawing
Platform: UNKNOWN
Classifier: Development Status :: 4 - Beta
Classifier: Intended Audience :: Developers
Classifier: Operating System :: OS Independent
Classifier: Topic :: Desktop Environment
Classifier: License :: OSI Approved :: BSD License
Classifier: Programming Language :: Python :: 3
Requires-Dist: wxpython (>=4.1.0)
